frostfire/__init__.py
frostfire/database.py
frostfire/functions.py
hungry4pizza-1.1.5.dist-info/LICENSE
hungry4pizza-1.1.5.dist-info/METADATA
hungry4pizza-1.1.5.dist-info/WHEEL
hungry4pizza-1.1.5.dist-info/top_level.txt
hungry4pizza-1.1.5.dist-info/RECORD
