Metadata-Version: 2.1
Name: hungry4pizza
Version: 1.1.5
Summary: Convenience functions.
Home-page: https://github.com/imhungryforpizza/hungry4pizza
Author: imhungryforpizza
Author-email: squander@ixiom.net
Project-URL: Bug Tracker, https://github.com/imhungryforpizza/hungry4pizza/issues
Classifier: Programming Language :: Python :: 3
Classifier: License :: OSI Approved :: MIT License
Classifier: Operating System :: OS Independent
Requires-Python: <3.10,>=3.6
License-File: LICENSE
Requires-Dist: pandas
Requires-Dist: mysql-connector-python
Requires-Dist: requests
